LogExportTable.py
setup.py
LogExportTable.egg-info/PKG-INFO
LogExportTable.egg-info/SOURCES.txt
LogExportTable.egg-info/dependency_links.txt
LogExportTable.egg-info/requires.txt
LogExportTable.egg-info/top_level.txt